dripy/__init__.py
dripy/dripy.py
dripy/lodestar.py
dripy/pason.py
dripy/survey.py
dripy-0.2.11.dist-info/LICENSE
dripy-0.2.11.dist-info/METADATA
dripy-0.2.11.dist-info/WHEEL
dripy-0.2.11.dist-info/top_level.txt
dripy-0.2.11.dist-info/RECORD
