Metadata-Version: 2.1
Name: dripy
Version: 0.2.11
Summary: Python tools for working with drilling data
Home-page: https://github.com/bthornton191/dripy
Author: Ben Thornton
Author-email: ben.thornton@mscsoftware.com
License: UNKNOWN
Platform: UNKNOWN
Classifier: Programming Language :: Python :: 3
Classifier: License :: OSI Approved :: MIT License
Classifier: Operating System :: Microsoft :: Windows
Requires-Dist: thornpy
Requires-Dist: numpy
Requires-Dist: pandas
Requires-Dist: scipy
Requires-Dist: matplotlib
Requires-Dist: lasio
